{
	"version": "0.3.22", 
	"suite": "unknown_suite", 
	"function_id": 100, 
	"function_name": "ManyAffine", 
	"maximization": false, 
	"algorithm": {"name": "SynergisticEvolutionAdaptiveRejuvenationGuidedExploration", "info": "algorithm_info"},
	"attributes": ["evaluations", "raw_y"],
	"scenarios": [
		{"dimension": 5,
		"path": "data_f100_ManyAffine/IOHprofiler_f100_DIM5.dat",
		"runs": [
			{"instance": 56, "evals": 10000, "best": {"evals": 8798, "y": 0.09384302946343086, "x": [-3.9517036907124017, -1.5892068491659264, -3.056018194053957, -4.697152085544588, 3.3504018394621236]}}
		]}
	]
}
