{
	"version": "0.3.22", 
	"suite": "unknown_suite", 
	"function_id": 100, 
	"function_name": "ManyAffine", 
	"maximization": false, 
	"algorithm": {"name": "JADEArchiveEvolution", "info": "algorithm_info"},
	"attributes": ["evaluations", "raw_y"],
	"scenarios": [
		{"dimension": 5,
		"path": "data_f100_ManyAffine/IOHprofiler_f100_DIM5.dat",
		"runs": [
			{"instance": 116, "evals": 10000, "best": {"evals": 5983, "y": 2.021148416835638e-11, "x": [2.971215430891672, -2.7160682685455395, -0.17696309868376098, -2.7709912302072435, 0.8714202004582318]}}
		]}
	]
}
