{
	"version": "0.3.22", 
	"suite": "unknown_suite", 
	"function_id": 100, 
	"function_name": "ManyAffine", 
	"maximization": false, 
	"algorithm": {"name": "SocietallyGuidedAdaptiveForager", "info": "algorithm_info"},
	"attributes": ["evaluations", "raw_y"],
	"scenarios": [
		{"dimension": 5,
		"path": "data_f100_ManyAffine/IOHprofiler_f100_DIM5.dat",
		"runs": [
			{"instance": 20, "evals": 10000, "best": {"evals": 3173, "y": 6.444393630347227e-11, "x": [0.3514430764698422, 2.0807028473786193, -2.950267577895869, -3.1509506345985034, -2.0282630788459284]}}
		]}
	]
}
