{
	"version": "0.3.22", 
	"suite": "unknown_suite", 
	"function_id": 100, 
	"function_name": "ManyAffine", 
	"maximization": false, 
	"algorithm": {"name": "JADEArchiveEvolution", "info": "algorithm_info"},
	"attributes": ["evaluations", "raw_y"],
	"scenarios": [
		{"dimension": 5,
		"path": "data_f100_ManyAffine/IOHprofiler_f100_DIM5.dat",
		"runs": [
			{"instance": 62, "evals": 10000, "best": {"evals": 4441, "y": 0.054788221851911095, "x": [-3.9161855189303907, -3.1577998496290793, -2.303440168732389, 4.442181717975373, -1.4944211472352011]}}
		]}
	]
}
