{
	"version": "0.3.22", 
	"suite": "unknown_suite", 
	"function_id": 100, 
	"function_name": "ManyAffine", 
	"maximization": false, 
	"algorithm": {"name": "AMR_DE_DynPopHybrid", "info": "algorithm_info"},
	"attributes": ["evaluations", "raw_y"],
	"scenarios": [
		{"dimension": 5,
		"path": "data_f100_ManyAffine/IOHprofiler_f100_DIM5.dat",
		"runs": [
			{"instance": 41, "evals": 10000, "best": {"evals": 6673, "y": 2.762327032718313e-12, "x": [2.1545012558486567, 2.7341056024546795, -3.6897571436604495, 4.505907386755078, -4.359253106391599]}}
		]}
	]
}
