{
	"version": "0.3.22", 
	"suite": "unknown_suite", 
	"function_id": 100, 
	"function_name": "ManyAffine", 
	"maximization": false, 
	"algorithm": {"name": "AdaptiveSynergisticDifferentialEvolution", "info": "algorithm_info"},
	"attributes": ["evaluations", "raw_y"],
	"scenarios": [
		{"dimension": 5,
		"path": "data_f100_ManyAffine/IOHprofiler_f100_DIM5.dat",
		"runs": [
			{"instance": 26, "evals": 10000, "best": {"evals": 5611, "y": 4.162680587696268e-11, "x": [-3.1443424329899043, 4.320521125725062, 1.2562687532886305, -0.5741719812893843, -4.8641201418063735]}}
		]}
	]
}
